Verilog-Files/src/Parameter.v
// =========================================================================
// Practical 4: StarCore-1 — Single-Cycle Processor in Verilog
// =========================================================================
//
// GROUP NUMBER:
//
// MEMBERS:
//   - Member 1 Name, Student Number
//   - Member 2 Name, Student Number

// File        : Parameter.v
// Description : Shared compile-time parameters used across all modules.
//               Include this file at the top of every .v file:
//                   `include "../src/Parameter.v"
// =============================================================================

`ifndef PARAMETER_H_
`define PARAMETER_H_

// ---------------------------------------------------------------------------
// Memory dimensions
// ---------------------------------------------------------------------------
`define COL     16          // Data/instruction word width (bits)
`define ROW_I   16          // Instruction memory depth (words, 16 x 16-bit)
`define ROW_D    8          // Data memory depth (words,  8 x 16-bit)

// ---------------------------------------------------------------------------
// Simulation control
// Increase SIM_TIME if your test program needs more clock cycles to complete.
// At 10 ns per clock (100 MHz) each #10 is one half-period; 320 ns = 16 cycles.
// ---------------------------------------------------------------------------
`define SIM_TIME  #160      // Total simulation time for integration testbench

// ---------------------------------------------------------------------------
// Output file for data-memory dump (used in DataMemory.v $fmonitor)
// ---------------------------------------------------------------------------
`define DMEM_LOG  "./waves/dmem_log.txt"

`endif  // PARAMETER_H_

Verilog-Files/src/DataMemory.v
// =========================================================================
// Practical 4: StarCore-1 — Single-Cycle Processor in Verilog
// =========================================================================
//
// GROUP NUMBER: 3
//
// MEMBERS:
//   - Thomas Kruger, KRGTHO002
//   - Tamryn Osler, OSLTAM001

// File        : DataMemory.v
// Description : Data Memory (RAM).
//               8 words × 16 bits. Contents loaded at simulation start from
//               the binary file ./test/test.data using $readmemb.
//               Writes are synchronous (positive-edge clocked).
//               Reads are combinational and gated by the mem_read enable.
//
// Task 4 — Student Implementation Required
// =============================================================================

`timescale 1ns / 1ps
`include "../src/Parameter.v"

module DataMemory (
    input        clk,

    // Shared address bus (used for both reads and writes)
    input  [15:0] mem_access_addr,  // Byte address; only lower bits used for indexing

    // Write port
    input  [15:0] mem_write_data,   // Data to store
    input        mem_write_en,      // Assert to write on the next posedge clk

    // Read port
    input        mem_read,          // Assert to enable the read output
    output [15:0] mem_read_data     // Read result; 16'd0 when mem_read is de-asserted
);

    // -------------------------------------------------------------------------
    // TODO: Declare the data memory array.
    //       It should hold `ROW_D entries, each `COL bits wide.
    //
    //       reg [`COL-1:0] memory [`ROW_D-1:0];
    // -------------------------------------------------------------------------
        reg[`COL-1:0] memory [`ROW_D-1:0];

    // -------------------------------------------------------------------------
    // TODO: Derive the word address from mem_access_addr.
    //       The data memory is 8 words deep so only 3 address bits are needed.
    //       The ALU computes a byte address; use the lower 3 bits as the index:
    //
    //           wire [2:0] ram_addr = mem_access_addr[2:0];
    //
    //       This maps byte addresses 0,1,2,3,4,5,6,7 to words 0–7.
    //       (In a full system the byte offset within a word would also be
    //       handled, but StarCore-1 only supports 16-bit aligned accesses.)
    // -------------------------------------------------------------------------
        wire [2:0] ram_addr = mem_access_addr[2:0];

    // -------------------------------------------------------------------------
    // TODO: Load the data memory from file at simulation start.
    //       The file ./test/test.data must contain one 16-bit binary value
    //       per line (8 lines total, one per word).
    //
    //       integer log_fd;
    //       initial begin
    //           $readmemb("./test/test.data", memory);
    //       end
    //
    //       Optional — add a $fmonitor to log memory contents to a file.
    //       This is useful for verifying ST instructions during simulation:
    //
    //       initial begin
    //           log_fd = $fopen(`DMEM_LOG);
    //           $fmonitor(log_fd, "t=%0t  [0]=%h [1]=%h [2]=%h [3]=%h",
    //                     $time, memory[0], memory[1], memory[2], memory[3]);
    //           `SIM_TIME;
    //           $fclose(log_fd);
    //       end
    // -------------------------------------------------------------------------
        integer log_fd;
        initial begin
            $readmemb("../test/test.data", memory);
        end


    // -------------------------------------------------------------------------
    // TODO: Implement the synchronous write port.
    //       Write mem_write_data to memory[ram_addr] on the rising clock edge
    //       when mem_write_en is asserted.
    //
    //       always @(posedge clk) begin
    //           if (mem_write_en)
    //               memory[ram_addr] <= mem_write_data;
    //       end
    //
    //       IMPORTANT: Use non-blocking assignment (<=).
    // -------------------------------------------------------------------------
        always @(posedge clk) begin
            if(mem_write_en)
                memory[ram_addr] <= mem_write_data;
        end

    // -------------------------------------------------------------------------
    // TODO: Implement the combinational (gated) read port.
    //       When mem_read is 1, output memory[ram_addr].
    //       When mem_read is 0, output 16'd0 (prevents spurious register writes
    //       during non-LD instructions).
    //
    //       assign mem_read_data = mem_read ? memory[ram_addr] : 16'd0;
    // -------------------------------------------------------------------------
        assign mem_read_data = mem_read ? memory[ram_addr] : 16'd0;

endmodule

StarCore1/tb/DataMemory_tb.v
// =============================================================================
// EEE4120F Practical 4 — StarCore-1 Processor
// File        : DataMemory_tb.v
// Description : Testbench for the Data Memory module (Task 4).
//               Verifies synchronous write, gated combinational read,
//               write followed by immediate read, and disabled-write safety.
//
// Run:
//   iverilog -Wall -I ../src -o ../build/dm_sim ../src/DataMemory.v DataMemory_tb.v
//   cd ../test && ../build/dm_sim
//   gtkwave ../waves/dm_tb.vcd &
// =============================================================================

`timescale 1ns / 1ps
`include "../src/Parameter.v"

module DataMemory_tb;

    reg        clk;
    reg  [15:0] mem_access_addr;
    reg  [15:0] mem_write_data;
    reg        mem_write_en;
    reg        mem_read;
    wire [15:0] mem_read_data;

    DataMemory uut (
        .clk             (clk),
        .mem_access_addr (mem_access_addr),
        .mem_write_data  (mem_write_data),
        .mem_write_en    (mem_write_en),
        .mem_read        (mem_read),
        .mem_read_data   (mem_read_data)
    );

    initial clk = 1'b0;
    always  #5 clk = ~clk;

    initial begin
        $dumpfile("../waves/dm_tb.vcd");
        $dumpvars(0, DataMemory_tb);
    end

    integer fail_count;
    integer test_id;

    initial begin
        fail_count      = 0;
        test_id         = 1;
        mem_write_en    = 1'b0;
        mem_read        = 1'b0;
        mem_access_addr = 16'd0;
        mem_write_data  = 16'd0;

        $display("=== DataMemory Testbench ===");

        // ------------------------------------------------------------------
        // TEST GROUP 1: Read back initial values loaded from test.data
        // ------------------------------------------------------------------
        $display("--- Group 1: Verify $readmemb initialisation ---");

        // TODO: Read each of the 8 memory locations and verify against
        //       the known contents of your test.data file.
        //       Remember: only mem_access_addr[2:0] is used as the index.
        //       Address 16'd0 -> word 0, address 16'd2 -> word 2, etc.
        //       (Or use address 16'd0 -> word 0, address 16'd1 -> word 1,
        //        since only the lower 3 bits matter.)
        //
        //       mem_read = 1'b1;
        //       mem_access_addr = 16'd0; #5;
        //       if (mem_read_data !== 16'h0001)  // expected value from test.data line 0
        //           $display("FAIL [T%0d]: addr=0 got=0x%h exp=0x0001", test_id, mem_read_data);
        //       else
        //           $display("PASS [T%0d]", test_id);
        //       test_id = test_id + 1;
            mem_read = 1'b1;

        mem_access_addr = 16'd0; #5;
        if (mem_read_data !== 16'h0001)
            $display("FAIL [T%0d]: addr=0 got=0x%h exp=0x0001", test_id, mem_read_data);
        else
            $display("PASS [T%0d]", test_id);
        test_id = test_id + 1;

        mem_access_addr = 16'd1; #5;
        if (mem_read_data !== 16'h0002)
            $display("FAIL [T%0d]: addr=1 got=0x%h exp=0x0002", test_id, mem_read_data);
        else
            $display("PASS [T%0d]", test_id);
        test_id = test_id + 1;

        mem_access_addr = 16'd2; #5;
        if (mem_read_data !== 16'h0003)
            $display("FAIL [T%0d]: addr=2 got=0x%h exp=0x0003", test_id, mem_read_data);
        else
            $display("PASS [T%0d]", test_id);
        test_id = test_id + 1;

        mem_access_addr = 16'd3; #5;
        if (mem_read_data !== 16'h0004)
            $display("FAIL [T%0d]: addr=3 got=0x%h exp=0x0004", test_id, mem_read_data);
        else
            $display("PASS [T%0d]", test_id);
        test_id = test_id + 1;

        mem_access_addr = 16'd4; #5;
        if (mem_read_data !== 16'h0005)
            $display("FAIL [T%0d]: addr=4 got=0x%h exp=0x0005", test_id, mem_read_data);
        else
            $display("PASS [T%0d]", test_id);
        test_id = test_id + 1;

        mem_access_addr = 16'd5; #5;
        if (mem_read_data !== 16'h0006)
            $display("FAIL [T%0d]: addr=5 got=0x%h exp=0x0006", test_id, mem_read_data);
        else
            $display("PASS [T%0d]", test_id);
        test_id = test_id + 1;

        mem_access_addr = 16'd6; #5;
        if (mem_read_data !== 16'h0007)
            $display("FAIL [T%0d]: addr=6 got=0x%h exp=0x0007", test_id, mem_read_data);
        else
            $display("PASS [T%0d]", test_id);
        test_id = test_id + 1;

        mem_access_addr = 16'd7; #5;
        if (mem_read_data !== 16'h0008)
            $display("FAIL [T%0d]: addr=7 got=0x%h exp=0x0008", test_id, mem_read_data);
        else
            $display("PASS [T%0d]", test_id);
        test_id = test_id + 1;

        mem_read = 1'b0;


        // ------------------------------------------------------------------
        // TEST GROUP 2: Write new values to all 8 locations, then read back
        // ------------------------------------------------------------------
        $display("--- Group 2: Write then read all 8 locations ---");

        // TODO: Write a distinct value to each of the 8 addresses using
        //       mem_write_en and posedge clk, then read each back.
        //
        //       // Write to address 0
        //       mem_write_en    = 1'b1;
        //       mem_access_addr = 16'd0;
        //       mem_write_data  = 16'hABCD;
        //       @(posedge clk); #1;
        //       mem_write_en    = 1'b0;
        //
        //       // Read back from address 0
        //       mem_read = 1'b1;
        //       mem_access_addr = 16'd0; #5;
        //       if (mem_read_data !== 16'hABCD) ...
        //       test_id = test_id + 1;

        // Write and read back address 0
        mem_write_en    = 1'b1;
        mem_access_addr = 16'd0;
        mem_write_data  = 16'hA000;
        @(posedge clk); #1;
        mem_write_en    = 1'b0;

        mem_read = 1'b1;
        mem_access_addr = 16'd0; #5;
        if (mem_read_data !== 16'hA000)
            $display("FAIL [T%0d]: addr=0 got=0x%h exp=0xA000", test_id, mem_read_data);
        else
            $display("PASS [T%0d]", test_id);
        test_id = test_id + 1;
        mem_read = 1'b0;

        // Write and read back address 1
        mem_write_en    = 1'b1;
        mem_access_addr = 16'd1;
        mem_write_data  = 16'hB001;
        @(posedge clk); #1;
        mem_write_en    = 1'b0;

        mem_read = 1'b1;
        mem_access_addr = 16'd1; #5;
        if (mem_read_data !== 16'hB001)
            $display("FAIL [T%0d]: addr=1 got=0x%h exp=0xB001", test_id, mem_read_data);
        else
            $display("PASS [T%0d]", test_id);
        test_id = test_id + 1;
        mem_read = 1'b0;

        // Write and read back address 2
        mem_write_en    = 1'b1;
        mem_access_addr = 16'd2;
        mem_write_data  = 16'hC002;
        @(posedge clk); #1;
        mem_write_en    = 1'b0;

        mem_read = 1'b1;
        mem_access_addr = 16'd2; #5;
        if (mem_read_data !== 16'hC002)
            $display("FAIL [T%0d]: addr=2 got=0x%h exp=0xC002", test_id, mem_read_data);
        else
            $display("PASS [T%0d]", test_id);
        test_id = test_id + 1;
        mem_read = 1'b0;

        // Write and read back address 3
        mem_write_en    = 1'b1;
        mem_access_addr = 16'd3;
        mem_write_data  = 16'hD003;
        @(posedge clk); #1;
        mem_write_en    = 1'b0;

        mem_read = 1'b1;
        mem_access_addr = 16'd3; #5;
        if (mem_read_data !== 16'hD003)
            $display("FAIL [T%0d]: addr=3 got=0x%h exp=0xD003", test_id, mem_read_data);
        else
            $display("PASS [T%0d]", test_id);
        test_id = test_id + 1;
        mem_read = 1'b0;

        // Write and read back address 4
        mem_write_en    = 1'b1;
        mem_access_addr = 16'd4;
        mem_write_data  = 16'hE004;
        @(posedge clk); #1;
        mem_write_en    = 1'b0;

        mem_read = 1'b1;
        mem_access_addr = 16'd4; #5;
        if (mem_read_data !== 16'hE004)
            $display("FAIL [T%0d]: addr=4 got=0x%h exp=0xE004", test_id, mem_read_data);
        else
            $display("PASS [T%0d]", test_id);
        test_id = test_id + 1;
        mem_read = 1'b0;

        // Write and read back address 5
        mem_write_en    = 1'b1;
        mem_access_addr = 16'd5;
        mem_write_data  = 16'hF005;
        @(posedge clk); #1;
        mem_write_en    = 1'b0;

        mem_read = 1'b1;
        mem_access_addr = 16'd5; #5;
        if (mem_read_data !== 16'hF005)
            $display("FAIL [T%0d]: addr=5 got=0x%h exp=0xF005", test_id, mem_read_data);
        else
            $display("PASS [T%0d]", test_id);
        test_id = test_id + 1;
        mem_read = 1'b0;

        // Write and read back address 6
        mem_write_en    = 1'b1;
        mem_access_addr = 16'd6;
        mem_write_data  = 16'h1006;
        @(posedge clk); #1;
        mem_write_en    = 1'b0;

        mem_read = 1'b1;
        mem_access_addr = 16'd6; #5;
        if (mem_read_data !== 16'h1006)
            $display("FAIL [T%0d]: addr=6 got=0x%h exp=0x1006", test_id, mem_read_data);
        else
            $display("PASS [T%0d]", test_id);
        test_id = test_id + 1;
        mem_read = 1'b0;

        // Write and read back address 7
        mem_write_en    = 1'b1;
        mem_access_addr = 16'd7;
        mem_write_data  = 16'h2007;
        @(posedge clk); #1;
        mem_write_en    = 1'b0;

        mem_read = 1'b1;
        mem_access_addr = 16'd7; #5;
        if (mem_read_data !== 16'h2007)
            $display("FAIL [T%0d]: addr=7 got=0x%h exp=0x2007", test_id, mem_read_data);
        else
            $display("PASS [T%0d]", test_id);
        test_id = test_id + 1;
        mem_read = 1'b0;

        // ------------------------------------------------------------------
        // TEST GROUP 3: mem_read = 0 must produce 16'd0 output
        // ------------------------------------------------------------------
        $display("--- Group 3: mem_read disabled -> output must be 0 ---");

        // TODO: De-assert mem_read and verify the output is 16'd0 regardless
        //       of the address.
        //
        //       mem_read = 1'b0;
        //       mem_access_addr = 16'd0; #5;
        //       if (mem_read_data !== 16'd0)
        //           $display("FAIL [T%0d]: mem_read=0 but output=%h", test_id, mem_read_data);
        //       else
        //           $display("PASS [T%0d]: output = 0 when mem_read=0", test_id);
        //       test_id = test_id + 1;
        mem_read = 1'b0;

        mem_access_addr = 16'd0; #5;
        if (mem_read_data !== 16'd0)
            $display("FAIL [T%0d]: mem_read=0 addr=0 but output=0x%h", test_id, mem_read_data);
        else
            $display("PASS [T%0d]: output = 0 when mem_read=0", test_id);
        test_id = test_id + 1;

        mem_access_addr = 16'd1; #5;
        if (mem_read_data !== 16'd0)
            $display("FAIL [T%0d]: mem_read=0 addr=1 but output=0x%h", test_id, mem_read_data);
        else
            $display("PASS [T%0d]: output = 0 when mem_read=0", test_id);
        test_id = test_id + 1;

        mem_access_addr = 16'd2; #5;
        if (mem_read_data !== 16'd0)
            $display("FAIL [T%0d]: mem_read=0 addr=2 but output=0x%h", test_id, mem_read_data);
        else
            $display("PASS [T%0d]: output = 0 when mem_read=0", test_id);
        test_id = test_id + 1;

        mem_access_addr = 16'd3; #5;
        if (mem_read_data !== 16'd0)
            $display("FAIL [T%0d]: mem_read=0 addr=3 but output=0x%h", test_id, mem_read_data);
        else
            $display("PASS [T%0d]: output = 0 when mem_read=0", test_id);
        test_id = test_id + 1;

        mem_access_addr = 16'd4; #5;
        if (mem_read_data !== 16'd0)
            $display("FAIL [T%0d]: mem_read=0 addr=4 but output=0x%h", test_id, mem_read_data);
        else
            $display("PASS [T%0d]: output = 0 when mem_read=0", test_id);
        test_id = test_id + 1;

        mem_access_addr = 16'd5; #5;
        if (mem_read_data !== 16'd0)
            $display("FAIL [T%0d]: mem_read=0 addr=5 but output=0x%h", test_id, mem_read_data);
        else
            $display("PASS [T%0d]: output = 0 when mem_read=0", test_id);
        test_id = test_id + 1;

        mem_access_addr = 16'd6; #5;
        if (mem_read_data !== 16'd0)
            $display("FAIL [T%0d]: mem_read=0 addr=6 but output=0x%h", test_id, mem_read_data);
        else
            $display("PASS [T%0d]: output = 0 when mem_read=0", test_id);
        test_id = test_id + 1;

        mem_access_addr = 16'd7; #5;
        if (mem_read_data !== 16'd0)
            $display("FAIL [T%0d]: mem_read=0 addr=7 but output=0x%h", test_id, mem_read_data);
        else
            $display("PASS [T%0d]: output = 0 when mem_read=0", test_id);
        test_id = test_id + 1;

        // ------------------------------------------------------------------
        // TEST GROUP 4: Write then immediately read on the next cycle
        // ------------------------------------------------------------------
        $display("--- Group 4: Write followed by immediate read ---");

        // TODO: Write to address 3, then on the very next cycle read back
        //       from address 3 and confirm the new value is returned.

        // Write to address 3
            mem_write_en    = 1'b1;
            mem_access_addr = 16'd3;
            mem_write_data  = 16'hBEEF;
            @(posedge clk); #1;
            mem_write_en    = 1'b0;

            // Immediately read back on the very next cycle
            mem_read        = 1'b1;
            mem_access_addr = 16'd3; #5;
            if (mem_read_data !== 16'hBEEF)
                $display("FAIL [T%0d]: immediate read after write got=0x%h exp=0xBEEF", test_id, mem_read_data);
            else
                $display("PASS [T%0d]: immediate read after write correct", test_id);
            test_id = test_id + 1;
            mem_read = 1'b0;

        // ------------------------------------------------------------------
        // TEST GROUP 5: Disabled write must not alter memory
        // ------------------------------------------------------------------
        $display("--- Group 5: mem_write_en=0 must not overwrite memory ---");

        // Attempt to overwrite address 3 with write enable deasserted
        mem_write_en    = 1'b0;
        mem_access_addr = 16'd3;
        mem_write_data  = 16'hDEAD;    // this value must NOT be written
        @(posedge clk); #1;

        // Read back and confirm 0xBEEF from Group 4 is still there
        mem_read        = 1'b1;
        mem_access_addr = 16'd3; #5;
        if (mem_read_data !== 16'hBEEF)
            $display("FAIL [T%0d]: disabled write corrupted memory got=0x%h exp=0xBEEF", test_id, mem_read_data);
        else
            $display("PASS [T%0d]: disabled write did not alter memory", test_id);
        test_id = test_id + 1;
        mem_read = 1'b0;

        $display("");
        if (fail_count == 0)
            $display("=== ALL %0d TESTS PASSED ===", test_id - 1);
        else
            $display("=== %0d / %0d TESTS FAILED ===", fail_count, test_id - 1);
        $finish;
    end

endmodule

Verilog-Files/waves/dm_tb.vcd
$date
	Tue Apr 21 18:37:12 2026
$end
$version
	Icarus Verilog
$end
$timescale
	1ps
$end
$scope module DataMemory_tb $end
$var wire 16 ! mem_read_data [15:0] $end
$var reg 1 " clk $end
$var reg 16 # mem_access_addr [15:0] $end
$var reg 1 $ mem_read $end
$var reg 16 % mem_write_data [15:0] $end
$var reg 1 & mem_write_en $end
$var integer 32 ' fail_count [31:0] $end
$var integer 32 ( test_id [31:0] $end
$scope module uut $end
$var wire 1 " clk $end
$var wire 16 ) mem_access_addr [15:0] $end
$var wire 1 $ mem_read $end
$var wire 16 * mem_write_data [15:0] $end
$var wire 1 & mem_write_en $end
$var wire 3 + ram_addr [2:0] $end
$var wire 16 , mem_read_data [15:0] $end
$upscope $end
$upscope $end
$enddefinitions $end
$comment Show the parameter values. $end
$dumpall
$end
#0
$dumpvars
bx ,
b0 +
b0 *
b0 )
b1 (
b0 '
0&
b0 %
1$
b0 #
0"
bx !
$end
#5000
b1 +
b1 #
b1 )
b10 (
1"
#10000
b10 +
b10 #
b10 )
b11 (
0"
#15000
b11 +
b11 #
b11 )
b100 (
1"
#20000
b100 +
b100 #
b100 )
b101 (
0"
#25000
b101 +
b101 #
b101 )
b110 (
1"
#30000
b110 +
b110 #
b110 )
b111 (
0"
#35000
b111 +
b111 #
b111 )
b1000 (
1"
#40000
b0 +
b0 !
b0 ,
b1010000000000000 %
b1010000000000000 *
b0 #
b0 )
1&
0$
b1001 (
0"
#45000
1"
#46000
b1010000000000000 !
b1010000000000000 ,
1$
0&
#50000
0"
#51000
b1 +
b0 !
b0 ,
b1011000000000001 %
b1011000000000001 *
b1 #
b1 )
1&
0$
b1010 (
#55000
1"
#56000
b1011000000000001 !
b1011000000000001 ,
1$
0&
#60000
0"
#61000
b10 +
b0 !
b0 ,
b1100000000000010 %
b1100000000000010 *
b10 #
b10 )
1&
0$
b1011 (
#65000
1"
#66000
b1100000000000010 !
b1100000000000010 ,
1$
0&
#70000
0"
#71000
b11 +
b0 !
b0 ,
b1101000000000011 %
b1101000000000011 *
b11 #
b11 )
1&
0$
b1100 (
#75000
1"
#76000
b1101000000000011 !
b1101000000000011 ,
1$
0&
#80000
0"
#81000
b100 +
b0 !
b0 ,
b1110000000000100 %
b1110000000000100 *
b100 #
b100 )
1&
0$
b1101 (
#85000
1"
#86000
b1110000000000100 !
b1110000000000100 ,
1$
0&
#90000
0"
#91000
b101 +
b0 !
b0 ,
b1111000000000101 %
b1111000000000101 *
b101 #
b101 )
1&
0$
b1110 (
#95000
1"
#96000
b1111000000000101 !
b1111000000000101 ,
1$
0&
#100000
0"
#101000
b110 +
b0 !
b0 ,
b1000000000110 %
b1000000000110 *
b110 #
b110 )
1&
0$
b1111 (
#105000
1"
#106000
b1000000000110 !
b1000000000110 ,
1$
0&
#110000
0"
#111000
b111 +
b0 !
b0 ,
b10000000000111 %
b10000000000111 *
b111 #
b111 )
1&
0$
b10000 (
#115000
1"
#116000
b10000000000111 !
b10000000000111 ,
1$
0&
#120000
0"
#121000
b0 +
b0 !
b0 ,
b0 #
b0 )
0$
b10001 (
#125000
1"
#126000
b1 +
b1 #
b1 )
b10010 (
#130000
0"
#131000
b10 +
b10 #
b10 )
b10011 (
#135000
1"
#136000
b11 +
b11 #
b11 )
b10100 (
#140000
0"
#141000
b100 +
b100 #
b100 )
b10101 (
#145000
1"
#146000
b101 +
b101 #
b101 )
b10110 (
#150000
0"
#151000
b110 +
b110 #
b110 )
b10111 (
#155000
1"
#156000
b111 +
b111 #
b111 )
b11000 (
#160000
0"
#161000
b11 +
b1011111011101111 %
b1011111011101111 *
b11 #
b11 )
1&
b11001 (
#165000
1"
#166000
b1011111011101111 !
b1011111011101111 ,
1$
0&
#170000
0"
#171000
b0 !
b0 ,
b1101111010101101 %
b1101111010101101 *
0$
b11010 (
#175000
1"
#176000
b1011111011101111 !
b1011111011101111 ,
1$
#180000
0"
#181000
b0 !
b0 ,
0$
b11011 (
